pycolouring/__init__.py
pycolouring/setup.py
pycolouring-0.1.3.dist-info/METADATA
pycolouring-0.1.3.dist-info/WHEEL
pycolouring-0.1.3.dist-info/top_level.txt
pycolouring-0.1.3.dist-info/RECORD
