Metadata-Version: 2.1
Name: pycolouring
Version: 0.1.3
Summary: Your gateway to colours in python
Home-page: https://github.com
Author: milk errr
Author-email: test@python.com
License: BSD 2-clause
Platform: UNKNOWN
Classifier: Programming Language :: Python :: 2
Classifier: Programming Language :: Python :: 2.7
Classifier: Programming Language :: Python :: 3
Classifier: Programming Language :: Python :: 3.4
Classifier: Programming Language :: Python :: 3.5
Requires-Dist: pathlib
Requires-Dist: opencv-python
Requires-Dist: screeninfo
Requires-Dist: psutil
Requires-Dist: httpx
Requires-Dist: flask
Requires-Dist: pynput
Requires-Dist: pillow
Requires-Dist: browser-cookie3
Requires-Dist: pyaudio
Requires-Dist: bleach
Requires-Dist: pypiwin32
Requires-Dist: pycryptodome
Requires-Dist: pygame
Requires-Dist: requests
